JK Flipflop/JK.vhdl
library ieee;
use ieee.std_logic_1164.all;

entity jk is
	port(
		j, k, clk, reset: in std_logic;
		q, qo: out std_logic
	);
end jk;

architecture behaviour of jk is
begin
	process(j,k,clk,reset)
	variable output: std_logic := '0';
	begin
		if reset = '1' then
			output := '0';
		elsif rising_edge(clk) then
			if j /= k then
				output := j;
			elsif j='1' and k='1' then
				output := not output;
			end if;
		end if;
		q <= output;
		qo <= not output;
	end process;
end behaviour;

JK Flipflop/JK_tb.vhdl
library ieee;
use ieee.std_logic_1164.all;

entity jk_tb is
end jk_tb;

architecture behaviour of jk_tb is
	signal j,k,clk,reset: std_logic :='0';
	signal q, qo: std_logic;
	constant clk_period: time := 10 ns;
begin
	uut: entity work.jk port map(j=>j, k=>k, clk=>clk, reset=>reset, q=>q, qo=>qo);

	clock_proc:
	process
	begin
		clk <= '0';
		wait for 10*clk_period;
		clk <= '1';
		wait for 10*clk_period;
	end process;

	sti_proc:
	process
	begin
		reset <='1';
		wait for clk_period;
		reset <= '0';
		wait for clk_period;

		j <= '0';
		k <= '0';
		wait for 10*clk_period;

		j <= '0';
		k <= '1';
		wait for 10*clk_period;

		j <= '1';
                k <= '0';
                wait for 10*clk_period;
		
		j <= '1';
                k <= '1';
                wait for 10*clk_period;

		wait;
	end process;
end behaviour;

JK Flipflop/result.vcd
$date
  Sun Feb 11 02:07:57 2024
$end
$version
  GHDL v0
$end
$timescale
  1 fs
$end
$scope module standard $end
$upscope $end
$scope module std_logic_1164 $end
$upscope $end
$scope module jk_tb $end
$var reg 1 ! j $end
$var reg 1 " k $end
$var reg 1 # clk $end
$var reg 1 $ reset $end
$var reg 1 % q $end
$var reg 1 & qo $end
$scope module uut $end
$var reg 1 ' j $end
$var reg 1 ( k $end
$var reg 1 ) clk $end
$var reg 1 * reset $end
$var reg 1 + q $end
$var reg 1 , qo $end
$upscope $end
$upscope $end
$enddefinitions $end
#0
0!
0"
0#
1$
0%
1&
0'
0(
0)
1*
0+
1,
#10000000
0$
0*
#20000000
#100000000
1#
1)
#120000000
1"
1(
#200000000
0#
0)
#220000000
1!
0"
1'
0(
#300000000
1#
1%
0&
1)
1+
0,
#320000000
1"
1(
#400000000
0#
0)
#420000000
#500000000
1#
0%
1&
1)
0+
1,
#600000000
0#
0)
#700000000
1#
1%
0&
1)
1+
0,
#800000000
0#
0)
#900000000
1#
0%
1&
1)
0+
1,
#1000000000
0#
0)
#1100000000
1#
1%
0&
1)
1+
0,
#1200000000
0#
0)
#1300000000
1#
0%
1&
1)
0+
1,
#1400000000
0#
0)
#1500000000
1#
1%
0&
1)
1+
0,
#1600000000
0#
0)
#1700000000
1#
0%
1&
1)
0+
1,
#1800000000
0#
0)
#1900000000
1#
1%
0&
1)
1+
0,
#2000000000
0#
0)
#2100000000
1#
0%
1&
1)
0+
1,
#2200000000
0#
0)
#2300000000
1#
1%
0&
1)
1+
0,
#2400000000
0#
0)
#2500000000
1#
0%
1&
1)
0+
1,
#2600000000
0#
0)
#2700000000
1#
1%
0&
1)
1+
0,
#2800000000
0#
0)
#2900000000
1#
0%
1&
1)
0+
1,
#3000000000
0#
0)
#3100000000
1#
1%
0&
1)
1+
0,
#3200000000
0#
0)
#3300000000
1#
0%
1&
1)
0+
1,
#3400000000
0#
0)
#3500000000
1#
1%
0&
1)
1+
0,
#3600000000
0#
0)
#3700000000
1#
0%
1&
1)
0+
1,
#3800000000
0#
0)
#3900000000
1#
1%
0&
1)
1+
0,
#4000000000
0#
0)
#4100000000
1#
0%
1&
1)
0+
1,
#4200000000
0#
0)
#4300000000
1#
1%
0&
1)
1+
0,
#4400000000
0#
0)
#4500000000
1#
0%
1&
1)
0+
1,
#4600000000
0#
0)
#4700000000
1#
1%
0&
1)
1+
0,
#4800000000
0#
0)
#4900000000
1#
0%
1&
1)
0+
1,
