Full adder/FULLADDER.vhdl
library	ieee;
use ieee.std_logic_1164.all;

entity or_gate is
	port(
		x,y: in	STD_LOGIC;
		z: out	STD_LOGIC
	);
end or_gate;

architecture behaviour of or_gate is
begin
	z <= x or y;
end behaviour;

-- for half adder
library	ieee;
use ieee.std_logic_1164.all;

entity half_adder is
	port(
		a,b: in STD_LOGIC;
		s,c: out STD_LOGIC
	);
end half_adder;

architecture behaviour of half_adder is
begin
	s <= a xor b;
	c <= a and b;
end behaviour;

--for full adder (using two half adder and an or gate)

library ieee;
use ieee.std_logic_1164.all;

entity full_adder is
	port(
		A,B,Cin: in STD_LOGIC;
		S,C: out STD_LOGIC
	);
end full_adder;

architecture behaviour of full_adder is
	component or_gate is
	port(
		x,y: in STD_LOGIC;
		z: out STD_LOGIC			
	);
	end component or_gate;

	component half_adder is
	port(
		a,b: in STD_LOGIC;
		s,c: out STD_LOGIC
	);
	end component half_adder;

	SIGNAL	S1,C1,C2:STD_LOGIC;
	BEGIN
		HA1: half_adder	PORT	MAP(a=>A,b=>B,s=>S1,c=>C1);
		HA2: half_adder	PORT	MAP(a=>S1,b=>Cin,s=>S,c=>C2);
		OR1: or_gate	PORT	MAP(x=>C1,y=>C2,z=>C);
end behaviour;

Full adder/FULLADDER_tb.vhdl
library ieee;
use ieee.std_logic_1164.all;

entity fa_test	is
end fa_test;

architecture test_bench of fa_test is
	component full_adder is
		port (
			A,B,Cin: in STD_LOGIC;
			S,C : out STD_LOGIC);
	end component full_adder;
	
	signal A,B,Cin,S,C: STD_LOGIC;

begin

	uut: full_adder port map(
			A=>A,	B=>B,
			Cin=>Cin,S=>S,C=>C
		);

	stim:	process
	begin
		A<='0';
		B<='0';
		Cin<='0';
		wait	for	10	ns;

		A<='0';
		B<='1';
		Cin<='0';
		wait	for	10	ns;
	
		A<='1';
		B<='0';
		Cin<='0';
		wait	for	10	ns;
	
		A<='1';
		B<='1';
		Cin<='0';
		wait for 10 ns;
		
		A<='0';
		B<='0';
		Cin<='1';
		wait	for	10	ns;

		A<='0';
		B<='1';
		Cin<='1';
		wait	for	10	ns;
	
		A<='1';
		B<='0';
		Cin<='1';
		wait	for	10	ns;
	
		A<='1';
		B<='1';
		Cin<='1';
		wait for 10 ns;
		wait;

	end process;
end test_bench;

Full adder/result.vcd
$date
  Mon Feb 19 07:37:45 2024
$end
$version
  GHDL v0
$end
$timescale
  1 fs
$end
$scope module standard $end
$upscope $end
$scope module std_logic_1164 $end
$upscope $end
$scope module fa_test $end
$var reg 1 ! a $end
$var reg 1 " b $end
$var reg 1 # cin $end
$var reg 1 $ s $end
$var reg 1 % c $end
$scope module uut $end
$var reg 1 & a $end
$var reg 1 ' b $end
$var reg 1 ( cin $end
$var reg 1 ) s $end
$var reg 1 * c $end
$var reg 1 + s1 $end
$var reg 1 , c1 $end
$var reg 1 - c2 $end
$scope module ha1 $end
$var reg 1 . a $end
$var reg 1 / b $end
$var reg 1 0 s $end
$var reg 1 1 c $end
$upscope $end
$scope module ha2 $end
$var reg 1 2 a $end
$var reg 1 3 b $end
$var reg 1 4 s $end
$var reg 1 5 c $end
$upscope $end
$scope module or1 $end
$var reg 1 6 x $end
$var reg 1 7 y $end
$var reg 1 8 z $end
$upscope $end
$upscope $end
$upscope $end
$enddefinitions $end
#0
0!
0"
0#
0$
0%
0&
0'
0(
0)
0*
0+
0,
0-
0.
0/
00
01
02
03
04
05
06
07
08
#10000000
1"
1$
1'
1)
1+
1/
10
12
14
#20000000
1!
0"
1&
0'
1.
0/
#30000000
1"
0$
1%
1'
0)
1*
0+
1,
1/
00
11
02
04
16
18
#40000000
0!
0"
1#
1$
0%
0&
0'
1(
1)
0*
0,
0.
0/
01
13
14
06
08
#50000000
1"
0$
1%
1'
0)
1*
1+
1-
1/
10
12
04
15
17
18
#60000000
1!
0"
1&
0'
1.
0/
#70000000
1"
1$
1'
1)
0+
1,
0-
1/
00
11
02
14
05
16
07
