BCD 7 counter/BCD.vhdl
library ieee;
use ieee.std_logic_1164.all;

entity bcd_seg is
	port(
		b0, b1, b2, b3: in std_logic;
		a, b, c, d, e, f, g: out std_logic
	);
end bcd_seg;

architecture behaviour of bcd_seg is
begin
	a <= b0 or b2 or (b1 and b3) or (not b1 and not b3);
	b <= (not b1) or (not b2 and not b3) or (b2 and b3);
	c <= b1 or not b2 or b3;
	d <= (not b1 and not b3) or (b2 and not b3) or (b1 and not b2 and b3) or (not b1 and b2) or b0;
	e <= (not b1 and not b3) or (b2 and not b3);
	f <= b0 or (not b2 and not b3) or (b1 and not b2) or (b1 and not b3);
	g <= b0 or (b1 and not b2) or ( not b1 and b2) or (b2 and not b3);

end behaviour;

BCD 7 counter/BCD_tb.vhdl
library ieee;
use ieee.std_logic_1164.all;
use ieee.numeric_std.all;

entity BCD_tb is
end BCD_tb;

architecture behaviour of BCD_tb is
    -- Component declaration for the unit under test
    component bcd_seg
        port (
            b0, b1, b2, b3: in std_logic;
            a, b, c, d, e, f, g: out std_logic
        );
    end component;

    -- Signals for testbench
    signal b0_tb, b1_tb, b2_tb, b3_tb: std_logic := '0';
    signal a_tb, b_tb, c_tb, d_tb, e_tb, f_tb, g_tb: std_logic;

begin
    -- Instantiate the unit under test
    UUT: bcd_seg port map (
        b0 => b0_tb,
        b1 => b1_tb,
        b2 => b2_tb,
        b3 => b3_tb,
        a => a_tb,
        b => b_tb,
        c => c_tb,
        d => d_tb,
        e => e_tb,
        f => f_tb,
        g => g_tb
    );

    -- Stimulus process
    stimulus: process
    begin
        -- Apply test vectors
        for i in 0 to 9 loop
            b3_tb <= std_logic(to_unsigned(i / 8, 1)(0));
            b2_tb <= std_logic(to_unsigned((i mod 8) / 4, 1)(0));
            b1_tb <= std_logic(to_unsigned((i mod 4) / 2, 1)(0));
            b0_tb <= std_logic(to_unsigned(i mod 2, 1)(0));

            -- Wait for a bit
            wait for 20 ns;

         
        end loop;

        -- Finish the simulation
        wait;
    end process;
    
end behaviour;

BCD 7 counter/result.vcd
$date
  Sun Feb 11 00:54:15 2024
$end
$version
  GHDL v0
$end
$timescale
  1 fs
$end
$scope module standard $end
$upscope $end
$scope module std_logic_1164 $end
$upscope $end
$scope module numeric_std $end
$upscope $end
$scope module bcd_tb $end
$var reg 1 ! b0_tb $end
$var reg 1 " b1_tb $end
$var reg 1 # b2_tb $end
$var reg 1 $ b3_tb $end
$var reg 1 % a_tb $end
$var reg 1 & b_tb $end
$var reg 1 ' c_tb $end
$var reg 1 ( d_tb $end
$var reg 1 ) e_tb $end
$var reg 1 * f_tb $end
$var reg 1 + g_tb $end
$scope module uut $end
$var reg 1 , b0 $end
$var reg 1 - b1 $end
$var reg 1 . b2 $end
$var reg 1 / b3 $end
$var reg 1 0 a $end
$var reg 1 1 b $end
$var reg 1 2 c $end
$var reg 1 3 d $end
$var reg 1 4 e $end
$var reg 1 5 f $end
$var reg 1 6 g $end
$upscope $end
$upscope $end
$enddefinitions $end
#0
0!
0"
0#
0$
1%
1&
1'
1(
1)
1*
0+
0,
0-
0.
0/
10
11
12
13
14
15
06
#20000000
1!
1+
1,
16
#40000000
0!
1"
0%
0(
0)
0,
1-
00
03
04
#60000000
1!
1%
1(
1,
10
13
#80000000
0!
0"
1#
0'
1)
0*
0,
0-
1.
02
14
05
#100000000
1!
1*
1,
15
#120000000
0!
1"
0&
1'
0,
1-
01
12
#140000000
1!
1,
#160000000
0!
0"
0#
1$
0%
1&
0(
0)
0*
0+
0,
0-
0.
1/
00
11
03
04
05
06
#180000000
1!
1%
1(
1*
1+
1,
10
13
15
16
