1 to 8 Demux/onetoeight.vhdl
library ieee;
use ieee.std_logic_1164.all;

entity demux is
	port(
		A, S0, S1, S2: in std_logic;
		y: out std_logic_vector (7 downto 0)
	);
end demux;

architecture behaviour of demux is
	signal select_signals: std_logic_vector(2 downto 0);
begin
	select_signals <= S2 & S1 & S0;
	process(select_signals)
	
	begin
		case select_signals is
			when "000" =>
				y <= (A, '0', '0', '0', '0', '0', '0', '0'); --output line 0 when s2,s1,s0 => `000`
			when "001" =>
				y <= ('0', A, '0', '0', '0', '0', '0', '0');
			when "010" =>
				y <= ('0', '0', A, '0', '0', '0', '0', '0');
			when "011" =>
				y <= ('0', '0', '0', A, '0', '0', '0', '0');
			when "100" =>
				y <= ('0', '0', '0', '0', A, '0', '0', '0');
			when "101" =>
				y <= ('0', '0', '0', '0', '0', A, '0', '0') ;
			when "110" =>
				y <= ('0', '0', '0', '0', '0', '0', A, '0');
			when "111" =>
				y <= ('0', '0', '0', '0', '0', '0', '0', A);
			when others =>
				y <= (others => '0'); --default: all output are zero
		end case;
	end process;
end behaviour;

1 to 8 Demux/onetoeight_tb.vhdl
library ieee;
use ieee.std_logic_1164.all;

entity onetoeight_tb is
end onetoeight_tb;

architecture behaviour of onetoeight_tb is
	signal A, S2, S1, S0: std_logic := '0';
	signal output_signal: std_logic_vector(7 downto 0);
	

	component demux
		port(
			A, S2, S1, S0: in std_logic;
			y: out std_logic_vector(7 downto 0)
		);
	end component;

begin
	UUT: demux port map(A => A, S2 => S2, S1 => S1, S0 => S0, y => output_signal);

	simulate_process: process 
	begin
		--test 0
		A <= '0';
		S2 <= '0';
		S1 <= '0';
		S0 <= '0';
		wait for 300 ns;

		--test 1
		A <= '1';
		S2 <= '0';
		S1 <= '0';
		S0 <= '0';
		wait for 300 ns;

		--test 2
		A <= '1';
		S2 <= '0';
		S1 <= '0';
		S0 <= '1';
		wait for 300 ns;

		--test 3
		A <= '1';
		S2 <= '0';
		S1 <= '1';
		S0 <= '0';
		wait for 300 ns;

		--test 4
		A <= '1';
		S2 <= '0';
		S1 <= '1';
		S0 <= '1';
		wait for 300 ns;

		--test 5
		A <= '1';
		S2 <= '1';
		S1 <= '0';
		S0 <= '0';
		wait for 300 ns;

		--test 6
		A <= '1';
		S2 <= '1';
		S1 <= '0';
		S0 <= '1';
		wait for 300 ns;

		--test 7
		A <= '1';
		S2 <= '1';
		S1 <= '1';
		S0 <= '1';
		wait for 300 ns;
		
		wait;
	end process;
end behaviour;

1 to 8 Demux/result.vcd
$date
  Sun Feb 11 00:48:38 2024
$end
$version
  GHDL v0
$end
$timescale
  1 fs
$end
$scope module standard $end
$upscope $end
$scope module std_logic_1164 $end
$upscope $end
$scope module onetoeight_tb $end
$var reg 1 ! a $end
$var reg 1 " s2 $end
$var reg 1 # s1 $end
$var reg 1 $ s0 $end
$var reg 8 % output_signal[7:0] $end
$scope module uut $end
$var reg 1 & a $end
$var reg 1 ' s0 $end
$var reg 1 ( s1 $end
$var reg 1 ) s2 $end
$var reg 8 * y[7:0] $end
$var reg 3 + select_signals[2:0] $end
$upscope $end
$upscope $end
$enddefinitions $end
#0
0!
0"
0#
0$
b00000000 %
0&
0'
0(
0)
b00000000 *
b000 +
#300000000
1!
1&
#600000000
1$
b01000000 %
1'
b01000000 *
b001 +
#900000000
1#
0$
b00100000 %
0'
1(
b00100000 *
b010 +
#1200000000
1$
b00010000 %
1'
b00010000 *
b011 +
#1500000000
1"
0#
0$
b00001000 %
0'
0(
1)
b00001000 *
b100 +
#1800000000
1$
b00000100 %
1'
b00000100 *
b101 +
#2100000000
1#
b00000001 %
1(
b00000001 *
b111 +
