Up Counter/upcounter.vhdl
library ieee;
use IEEE.STD_LOGIC_1164.ALL;

entity TFF is
    Port ( T, CLK, RST : in STD_LOGIC;
           Q : out STD_LOGIC);
end TFF;

architecture TFF of TFF is
    signal Q_temp : STD_LOGIC;
begin
    process (CLK, RST)
    begin
        if RST = '1' then
            Q_temp <= '0';   
        elsif rising_edge(CLK) then
            if T = '1' then
                Q_temp <= not Q_temp; 
            else
                Q_temp <= Q_temp;  
            end if;
        end if;
    end process;

    Q <= Q_temp; 
end TFF;

library IEEE;
use IEEE.STD_LOGIC_1164.ALL;

entity AND_G is
    Port ( A, B : in STD_LOGIC;
           Z : out STD_LOGIC);
end AND_G;

architecture AND_G of AND_G is
BEGIN
	Z <= A and B;

end AND_G;



library IEEE;
use IEEE.STD_LOGIC_1164.ALL;

entity up_counter is
    Port ( CLK, RST : in STD_LOGIC;
           Q : out STD_LOGIC_VECTOR(2 downto 0));
end up_counter;

architecture up_counter of up_counter is
	component AND_G is 
		port(A, B : in STD_LOGIC;
		    Z : out STD_LOGIC);
	end component AND_G;

	component TFF is
		Port ( T, CLK, RST : in STD_LOGIC;
		       Q : out STD_LOGIC);
	end component TFF;
signal QA, QB, QC, TC: STD_LOGIC;

BEGIN
	T1: TFF port map(T=>'1', CLK=> CLK, RST=>RST, Q=>QA);
	T2: TFF port map(T=>QA, CLK=>CLK, RST=>RST, Q=>QB);
	A1: AND_G port map(A=> QA, B=>QB, Z=>TC);
	T3: TFF port map(T=>TC, CLK=> CLK, RST=>RST, Q=>Q(2));
	Q(0)<= '1' when QA = '1' else '0';
	Q(1)<= '1' when QB = '1' else '0';


    
end up_counter;

upCounter/upCountertest.vhdl
library ieee;
use ieee.std_logic_1164.all;

entity up_counter_tb is
end up_counter_tb;

architecture tb_arch of up_counter_tb is
    -- Constants
    constant CLK_PERIOD: time := 10 ns;

    -- Signals
    signal CLK, RST: std_logic := '0';
    signal Q: std_logic_vector(2 downto 0);

begin
    -- Instantiate DUT (Design Under Test)
    DUT: entity work.up_counter
    port map (
        CLK => CLK,
        RST => RST,
        Q => Q
    );

    -- Clock process
    CLK_process: process
    begin
        CLK <= '0';
        wait for CLK_PERIOD / 2;
        CLK <= '1';
        wait for CLK_PERIOD / 2;
    end process;

    -- Stimulus process
    stimulus_process: process
    begin
        RST <= '1'; -- Reset
        wait for CLK_PERIOD * 5;
        RST <= '0'; -- Release Reset

        -- Test some inputs
        wait for CLK_PERIOD * 10;

        -- Add more test cases here if needed

        wait;
    end process;

end tb_arch;

upCounter/result.vcd
$date
  Tue Feb 13 15:36:03 2024
$end
$version
  GHDL v0
$end
$timescale
  1 fs
$end
$scope module standard $end
$upscope $end
$scope module std_logic_1164 $end
$upscope $end
$scope module up_counter_tb $end
$var reg 1 ! clk $end
$var reg 1 " rst $end
$var reg 3 # q[2:0] $end
$scope module dut $end
$var reg 1 $ clk $end
$var reg 1 % rst $end
$var reg 3 & q[2:0] $end
$var reg 1 ' qa $end
$var reg 1 ( qb $end
$var reg 1 ) qc $end
$var reg 1 * tc $end
$scope module t1 $end
$var reg 1 + t $end
$var reg 1 , clk $end
$var reg 1 - rst $end
$var reg 1 . q $end
$var reg 1 / q_temp $end
$upscope $end
$scope module t2 $end
$var reg 1 0 t $end
$var reg 1 1 clk $end
$var reg 1 2 rst $end
$var reg 1 3 q $end
$var reg 1 4 q_temp $end
$upscope $end
$scope module a1 $end
$var reg 1 5 a $end
$var reg 1 6 b $end
$var reg 1 7 z $end
$upscope $end
$scope module t3 $end
$var reg 1 8 t $end
$var reg 1 9 clk $end
$var reg 1 : rst $end
$var reg 1 ; q $end
$var reg 1 < q_temp $end
$upscope $end
$upscope $end
$upscope $end
$enddefinitions $end
#0
0!
1"
b000 #
0$
1%
b000 &
0'
0(
U)
0*
1+
0,
1-
0.
0/
00
01
12
03
04
05
06
07
08
09
1:
0;
0<
#5000000
1!
1$
1,
11
19
#10000000
0!
0$
0,
01
09
#15000000
1!
1$
1,
11
19
#20000000
0!
0$
0,
01
09
#25000000
1!
1$
1,
11
19
#30000000
0!
0$
0,
01
09
#35000000
1!
1$
1,
11
19
#40000000
0!
0$
0,
01
09
#45000000
1!
1$
1,
11
19
#50000000
0!
0"
0$
0%
0,
0-
01
02
09
0:
#55000000
1!
b001 #
1$
b001 &
1'
1,
1.
1/
10
11
15
19
#60000000
0!
0$
0,
01
09
#65000000
1!
b010 #
1$
b010 &
0'
1(
1,
0.
0/
00
11
13
14
05
16
19
#70000000
0!
0$
0,
01
09
#75000000
1!
b011 #
1$
b011 &
1'
1*
1,
1.
1/
10
11
15
17
18
19
#80000000
0!
0$
0,
01
09
#85000000
1!
b100 #
1$
b100 &
0'
0(
0*
1,
0.
0/
00
11
03
04
05
06
07
08
19
1;
1<
#90000000
0!
0$
0,
01
09
#95000000
1!
b101 #
1$
b101 &
1'
1,
1.
1/
10
11
15
19
#100000000
0!
0$
0,
01
09
#105000000
1!
b110 #
1$
b110 &
0'
1(
1,
0.
0/
00
11
13
14
05
16
19
#110000000
0!
0$
0,
01
09
#115000000
1!
b111 #
1$
b111 &
1'
1*
1,
1.
1/
10
11
15
17
18
19
#120000000
0!
0$
0,
01
09
#125000000
1!
b000 #
1$
b000 &
0'
0(
0*
1,
0.
0/
00
11
03
04
05
06
07
08
19
0;
0<
#130000000
0!
0$
0,
01
09
#135000000
1!
b001 #
1$
b001 &
1'
1,
1.
1/
10
11
15
19
#140000000
0!
0$
0,
01
09
#145000000
1!
b010 #
1$
b010 &
0'
1(
1,
0.
0/
00
11
13
14
05
16
19
#150000000
0!
0$
0,
01
09
#155000000
1!
b011 #
1$
b011 &
1'
1*
1,
1.
1/
10
11
15
17
18
19
#160000000
0!
0$
0,
01
09
#165000000
1!
b100 #
1$
b100 &
0'
0(
0*
1,
0.
0/
00
11
03
04
05
06
07
08
19
1;
1<
#170000000
0!
0$
0,
01
09
#175000000
1!
b101 #
1$
b101 &
1'
1,
1.
1/
10
11
15
19
#180000000
0!
0$
0,
01
09
#185000000
1!
b110 #
1$
b110 &
0'
1(
1,
0.
0/
00
11
13
14
05
16
19
#190000000
0!
0$
0,
01
09
#195000000
1!
b111 #
1$
b111 &
1'
1*
1,
1.
1/
10
11
15
17
18
19
#200000000
0!
0$
0,
01
09
#205000000
1!
b000 #
1$
b000 &
0'
0(
0*
1,
0.
0/
00
11
03
04
05
06
07
08
19
0;
0<
#210000000
0!
0$
0,
01
09
#215000000
1!
b001 #
1$
b001 &
1'
1,
1.
1/
10
11
15
19
#220000000
0!
0$
0,
01
09
#225000000
1!
b010 #
1$
b010 &
0'
1(
1,
0.
0/
00
11
13
14
05
16
19
#230000000
0!
0$
0,
01
09
#235000000
1!
b011 #
1$
b011 &
1'
1*
1,
1.
1/
10
11
15
17
18
19
#240000000
0!
0$
0,
01
09
#245000000
1!
b100 #
1$
b100 &
0'
0(
0*
1,
0.
0/
00
11
03
04
05
06
07
08
19
1;
1<
#250000000
0!
0$
0,
01
09
#255000000
1!
b101 #
1$
b101 &
1'
1,
1.
1/
10
11
15
19
#260000000
0!
0$
0,
01
09
#265000000
1!
b110 #
1$
b110 &
0'
1(
1,
0.
0/
00
11
13
14
05
16
19
#270000000
0!
0$
0,
01
09
#275000000
1!
b111 #
1$
b111 &
1'
1*
1,
1.
1/
10
11
15
17
18
19
#280000000
0!
0$
0,
01
09
#285000000
1!
b000 #
1$
b000 &
0'
0(
0*
1,
0.
0/
00
11
03
04
05
06
07
08
19
0;
0<
#290000000
0!
0$
0,
01
09
#295000000
1!
b001 #
1$
b001 &
1'
1,
1.
1/
10
11
15
19
#300000000
0!
0$
0,
01
09
#305000000
1!
b010 #
1$
b010 &
0'
1(
1,
0.
0/
00
11
13
14
05
16
19
#310000000
0!
0$
0,
01
09
#315000000
1!
b011 #
1$
b011 &
1'
1*
1,
1.
1/
10
11
15
17
18
19
#320000000
0!
0$
0,
01
09
#325000000
1!
b100 #
1$
b100 &
0'
0(
0*
1,
0.
0/
00
11
03
04
05
06
07
08
19
1;
1<
#330000000
0!
0$
0,
01
09
#335000000
1!
b101 #
1$
b101 &
1'
1,
1.
1/
10
11
15
19
#340000000
0!
0$
0,
01
09
#345000000
1!
b110 #
1$
b110 &
0'
1(
1,
0.
0/
00
11
13
14
05
16
19
#350000000
0!
0$
0,
01
09
#355000000
1!
b111 #
1$
b111 &
1'
1*
1,
1.
1/
10
11
15
17
18
19
#360000000
0!
0$
0,
01
09
#365000000
1!
b000 #
1$
b000 &
0'
0(
0*
1,
0.
0/
00
11
03
04
05
06
07
08
19
0;
0<
#370000000
0!
0$
0,
01
09
#375000000
1!
b001 #
1$
b001 &
1'
1,
1.
1/
10
11
15
19
#380000000
0!
0$
0,
01
09
#385000000
1!
b010 #
1$
b010 &
0'
1(
1,
0.
0/
00
11
13
14
05
16
19
#390000000
0!
0$
0,
01
09
#395000000
1!
b011 #
1$
b011 &
1'
1*
1,
1.
1/
10
11
15
17
18
19
#400000000
0!
0$
0,
01
09
#405000000
1!
b100 #
1$
b100 &
0'
0(
0*
1,
0.
0/
00
11
03
04
05
06
07
08
19
1;
1<
#410000000
0!
0$
0,
01
09
#415000000
1!
b101 #
1$
b101 &
1'
1,
1.
1/
10
11
15
19
#420000000
0!
0$
0,
01
09
#425000000
1!
b110 #
1$
b110 &
0'
1(
1,
0.
0/
00
11
13
14
05
16
19
#430000000
0!
0$
0,
01
09
#435000000
1!
b111 #
1$
b111 &
1'
1*
1,
1.
1/
10
11
15
17
18
19
#440000000
0!
0$
0,
01
09
#445000000
1!
b000 #
1$
b000 &
0'
0(
0*
1,
0.
0/
00
11
03
04
05
06
07
08
19
0;
0<
#450000000
0!
0$
0,
01
09
#455000000
1!
b001 #
1$
b001 &
1'
1,
1.
1/
10
11
15
19
#460000000
0!
0$
0,
01
09
#465000000
1!
b010 #
1$
b010 &
0'
1(
1,
0.
0/
00
11
13
14
05
16
19
#470000000
0!
0$
0,
01
09
#475000000
1!
b011 #
1$
b011 &
1'
1*
1,
1.
1/
10
11
15
17
18
19
#480000000
0!
0$
0,
01
09
#485000000
1!
b100 #
1$
b100 &
0'
0(
0*
1,
0.
0/
00
11
03
04
05
06
07
08
19
1;
1<
#490000000
0!
0$
0,
01
09
#495000000
1!
b101 #
1$
b101 &
1'
1,
1.
1/
10
11
15
19
#500000000
0!
0$
0,
01
09
#505000000
1!
b110 #
1$
b110 &
0'
1(
1,
0.
0/
00
11
13
14
05
16
19
#510000000
0!
0$
0,
01
09
#515000000
1!
b111 #
1$
b111 &
1'
1*
1,
1.
1/
10
11
15
17
18
19
#520000000
0!
0$
0,
01
09
#525000000
1!
b000 #
1$
b000 &
0'
0(
0*
1,
0.
0/
00
11
03
04
05
06
07
08
19
0;
0<
#530000000
0!
0$
0,
01
09
#535000000
1!
b001 #
1$
b001 &
1'
1,
1.
1/
10
11
15
19
#540000000
0!
0$
0,
01
09
#545000000
1!
b010 #
1$
b010 &
0'
1(
1,
0.
0/
00
11
13
14
05
16
19
#550000000
0!
0$
0,
01
09
#555000000
1!
b011 #
1$
b011 &
1'
1*
1,
1.
1/
10
11
15
17
18
19
#560000000
0!
0$
0,
01
09
#565000000
1!
b100 #
1$
b100 &
0'
0(
0*
1,
0.
0/
00
11
03
04
05
06
07
08
19
1;
1<
#570000000
0!
0$
0,
01
09
#575000000
1!
b101 #
1$
b101 &
1'
1,
1.
1/
10
11
15
19
#580000000
0!
0$
0,
01
09
#585000000
1!
b110 #
1$
b110 &
0'
1(
1,
0.
0/
00
11
13
14
05
16
19
#590000000
0!
0$
0,
01
09
#595000000
1!
b111 #
1$
b111 &
1'
1*
1,
1.
1/
10
11
15
17
18
19
#600000000
0!
0$
0,
01
09
#605000000
1!
b000 #
1$
b000 &
0'
0(
0*
1,
0.
0/
00
11
03
04
05
06
07
08
19
0;
0<
#610000000
0!
0$
0,
01
09
#615000000
1!
b001 #
1$
b001 &
1'
1,
1.
1/
10
11
15
19
#620000000
0!
0$
0,
01
09
#625000000
1!
b010 #
1$
b010 &
0'
1(
1,
0.
0/
00
11
13
14
05
16
19
#630000000
0!
0$
0,
01
09
#635000000
1!
b011 #
1$
b011 &
1'
1*
1,
1.
1/
10
11
15
17
18
19
#640000000
0!
0$
0,
01
09
#645000000
1!
b100 #
1$
b100 &
0'
0(
0*
1,
0.
0/
00
11
03
04
05
06
07
08
19
1;
1<
#650000000
0!
0$
0,
01
09
#655000000
1!
b101 #
1$
b101 &
1'
1,
1.
1/
10
11
15
19
#660000000
0!
0$
0,
01
09
#665000000
1!
b110 #
1$
b110 &
0'
1(
1,
0.
0/
00
11
13
14
05
16
19
#670000000
0!
0$
0,
01
09
#675000000
1!
b111 #
1$
b111 &
1'
1*
1,
1.
1/
10
11
15
17
18
19
#680000000
0!
0$
0,
01
09
#685000000
1!
b000 #
1$
b000 &
0'
0(
0*
1,
0.
0/
00
11
03
04
05
06
07
08
19
0;
0<
#690000000
0!
0$
0,
01
09
#695000000
1!
b001 #
1$
b001 &
1'
1,
1.
1/
10
11
15
19
#700000000
0!
0$
0,
01
09
#705000000
1!
b010 #
1$
b010 &
0'
1(
1,
0.
0/
00
11
13
14
05
16
19
#710000000
0!
0$
0,
01
09
#715000000
1!
b011 #
1$
b011 &
1'
1*
1,
1.
1/
10
11
15
17
18
19
#720000000
0!
0$
0,
01
09
#725000000
1!
b100 #
1$
b100 &
0'
0(
0*
1,
0.
0/
00
11
03
04
05
06
07
08
19
1;
1<
#730000000
0!
0$
0,
01
09
#735000000
1!
b101 #
1$
b101 &
1'
1,
1.
1/
10
11
15
19
#740000000
0!
0$
0,
01
09
#745000000
1!
b110 #
1$
b110 &
0'
1(
1,
0.
0/
00
11
13
14
05
16
19
#750000000
0!
0$
0,
01
09
#755000000
1!
b111 #
1$
b111 &
1'
1*
1,
1.
1/
10
11
15
17
18
19
#760000000
0!
0$
0,
01
09
#765000000
1!
b000 #
1$
b000 &
0'
0(
0*
1,
0.
0/
00
11
03
04
05
06
07
08
19
0;
0<
#770000000
0!
0$
0,
01
09
#775000000
1!
b001 #
1$
b001 &
1'
1,
1.
1/
10
11
15
19
#780000000
0!
0$
0,
01
09
#785000000
1!
b010 #
1$
b010 &
0'
1(
1,
0.
0/
00
11
13
14
05
16
19
#790000000
0!
0$
0,
01
09
#795000000
1!
b011 #
1$
b011 &
1'
1*
1,
1.
1/
10
11
15
17
18
19
#800000000
0!
0$
0,
01
09
#805000000
1!
b100 #
1$
b100 &
0'
0(
0*
1,
0.
0/
00
11
03
04
05
06
07
08
19
1;
1<
#810000000
0!
0$
0,
01
09
#815000000
1!
b101 #
1$
b101 &
1'
1,
1.
1/
10
11
15
19
#820000000
0!
0$
0,
01
09
#825000000
1!
b110 #
1$
b110 &
0'
1(
1,
0.
0/
00
11
13
14
05
16
19
#830000000
0!
0$
0,
01
09
#835000000
1!
b111 #
1$
b111 &
1'
1*
1,
1.
1/
10
11
15
17
18
19
#840000000
0!
0$
0,
01
09
#845000000
1!
b000 #
1$
b000 &
0'
0(
0*
1,
0.
0/
00
11
03
04
05
06
07
08
19
0;
0<
#850000000
0!
0$
0,
01
09
#855000000
1!
b001 #
1$
b001 &
1'
1,
1.
1/
10
11
15
19
#860000000
0!
0$
0,
01
09
#865000000
1!
b010 #
1$
b010 &
0'
1(
1,
0.
0/
00
11
13
14
05
16
19
#870000000
0!
0$
0,
01
09
#875000000
1!
b011 #
1$
b011 &
1'
1*
1,
1.
1/
10
11
15
17
18
19
#880000000
0!
0$
0,
01
09
#885000000
1!
b100 #
1$
b100 &
0'
0(
0*
1,
0.
0/
00
11
03
04
05
06
07
08
19
1;
1<
#890000000
0!
0$
0,
01
09
#895000000
1!
b101 #
1$
b101 &
1'
1,
1.
1/
10
11
15
19
#900000000
0!
0$
0,
01
09
#905000000
1!
b110 #
1$
b110 &
0'
1(
1,
0.
0/
00
11
13
14
05
16
19
#910000000
0!
0$
0,
01
09
#915000000
1!
b111 #
1$
b111 &
1'
1*
1,
1.
1/
10
11
15
17
18
19
#920000000
0!
0$
0,
01
09
#925000000
1!
b000 #
1$
b000 &
0'
0(
0*
1,
0.
0/
00
11
03
04
05
06
07
08
19
0;
0<
#930000000
0!
0$
0,
01
09
#935000000
1!
b001 #
1$
b001 &
1'
1,
1.
1/
10
11
15
19
#940000000
0!
0$
0,
01
09
#945000000
1!
b010 #
1$
b010 &
0'
1(
1,
0.
0/
00
11
13
14
05
16
19
#950000000
0!
0$
0,
01
09
#955000000
1!
b011 #
1$
b011 &
1'
1*
1,
1.
1/
10
11
15
17
18
19
#960000000
0!
0$
0,
01
09
#965000000
1!
b100 #
1$
b100 &
0'
0(
0*
1,
0.
0/
00
11
03
04
05
06
07
08
19
1;
1<
#970000000
0!
0$
0,
01
09
#975000000
1!
b101 #
1$
b101 &
1'
1,
1.
1/
10
11
15
19
#980000000
0!
0$
0,
01
09
#985000000
1!
b110 #
1$
b110 &
0'
1(
1,
0.
0/
00
11
13
14
05
16
19
#990000000
0!
0$
0,
01
09
#995000000
1!
b111 #
1$
b111 &
1'
1*
1,
1.
1/
10
11
15
17
18
19
#1000000000
0!
0$
0,
01
09
#1005000000
1!
b000 #
1$
b000 &
0'
0(
0*
1,
0.
0/
00
11
03
04
05
06
07
08
19
0;
0<
#1010000000
0!
0$
0,
01
09
#1015000000
1!
b001 #
1$
b001 &
1'
1,
1.
1/
10
11
15
19
#1020000000
0!
0$
0,
01
09
#1025000000
1!
b010 #
1$
b010 &
0'
1(
1,
0.
0/
00
11
13
14
05
16
19
#1030000000
0!
0$
0,
01
09
#1035000000
1!
b011 #
1$
b011 &
1'
1*
1,
1.
1/
10
11
15
17
18
19
#1040000000
0!
0$
0,
01
09
#1045000000
1!
b100 #
1$
b100 &
0'
0(
0*
1,
0.
0/
00
11
03
04
05
06
07
08
19
1;
1<
#1050000000
0!
0$
0,
01
09
#1055000000
1!
b101 #
1$
b101 &
1'
1,
1.
1/
10
11
15
19
#1060000000
0!
0$
0,
01
09
#1065000000
1!
b110 #
1$
b110 &
0'
1(
1,
0.
0/
00
11
13
14
05
16
19
#1070000000
0!
0$
0,
01
09
#1075000000
1!
b111 #
1$
b111 &
1'
1*
1,
1.
1/
10
11
15
17
18
19
#1080000000
0!
0$
0,
01
09
#1085000000
1!
b000 #
1$
b000 &
0'
0(
0*
1,
0.
0/
00
11
03
04
05
06
07
08
19
0;
0<
#1090000000
0!
0$
0,
01
09
#1095000000
1!
b001 #
1$
b001 &
1'
1,
1.
1/
10
11
15
19
#1100000000
0!
0$
0,
01
09
#1105000000
1!
b010 #
1$
b010 &
0'
1(
1,
0.
0/
00
11
13
14
05
16
19
#1110000000
0!
0$
0,
01
09
#1115000000
1!
b011 #
1$
b011 &
1'
1*
1,
1.
1/
10
11
15
17
18
19
#1120000000
0!
0$
0,
01
09
#1125000000
1!
b100 #
1$
b100 &
0'
0(
0*
1,
0.
0/
00
11
03
04
05
06
07
08
19
1;
1<
#1130000000
0!
0$
0,
01
09
#1135000000
1!
b101 #
1$
b101 &
1'
1,
1.
1/
10
11
15
19
#1140000000
0!
0$
0,
01
09
#1145000000
1!
b110 #
1$
b110 &
0'
1(
1,
0.
0/
00
11
13
14
05
16
19
#1150000000
0!
0$
0,
01
09
#1155000000
1!
b111 #
1$
b111 &
1'
1*
1,
1.
1/
10
11
15
17
18
19
#1160000000
0!
0$
0,
01
09
#1165000000
1!
b000 #
1$
b000 &
0'
0(
0*
1,
0.
0/
00
11
03
04
05
06
07
08
19
0;
0<
#1170000000
0!
0$
0,
01
09
#1175000000
1!
b001 #
1$
b001 &
1'
1,
1.
1/
10
11
15
19
#1180000000
0!
0$
0,
01
09
#1185000000
1!
b010 #
1$
b010 &
0'
1(
1,
0.
0/
00
11
13
14
05
16
19
#1190000000
0!
0$
0,
01
09
#1195000000
1!
b011 #
1$
b011 &
1'
1*
1,
1.
1/
10
11
15
17
18
19
#1200000000
0!
0$
0,
01
09
#1205000000
1!
b100 #
1$
b100 &
0'
0(
0*
1,
0.
0/
00
11
03
04
05
06
07
08
19
1;
1<
#1210000000
0!
0$
0,
01
09
#1215000000
1!
b101 #
1$
b101 &
1'
1,
1.
1/
10
11
15
19
#1220000000
0!
0$
0,
01
09
#1225000000
1!
b110 #
1$
b110 &
0'
1(
1,
0.
0/
00
11
13
14
05
16
19
#1230000000
0!
0$
0,
01
09
#1235000000
1!
b111 #
1$
b111 &
1'
1*
1,
1.
1/
10
11
15
17
18
19
#1240000000
0!
0$
0,
01
09
#1245000000
1!
b000 #
1$
b000 &
0'
0(
0*
1,
0.
0/
00
11
03
04
05
06
07
08
19
0;
0<
#1250000000
0!
0$
0,
01
09
#1255000000
1!
b001 #
1$
b001 &
1'
1,
1.
1/
10
11
15
19
#1260000000
0!
0$
0,
01
09
#1265000000
1!
b010 #
1$
b010 &
0'
1(
1,
0.
0/
00
11
13
14
05
16
19
#1270000000
0!
0$
0,
01
09
#1275000000
1!
b011 #
1$
b011 &
1'
1*
1,
1.
1/
10
11
15
17
18
19
#1280000000
0!
0$
0,
01
09
#1285000000
1!
b100 #
1$
b100 &
0'
0(
0*
1,
0.
0/
00
11
03
04
05
06
07
08
19
1;
1<
#1290000000
0!
0$
0,
01
09
#1295000000
1!
b101 #
1$
b101 &
1'
1,
1.
1/
10
11
15
19
#1300000000
0!
0$
0,
01
09
#1305000000
1!
b110 #
1$
b110 &
0'
1(
1,
0.
0/
00
11
13
14
05
16
19
#1310000000
0!
0$
0,
01
09
#1315000000
1!
b111 #
1$
b111 &
1'
1*
1,
1.
1/
10
11
15
17
18
19
#1320000000
0!
0$
0,
01
09
#1325000000
1!
b000 #
1$
b000 &
0'
0(
0*
1,
0.
0/
00
11
03
04
05
06
07
08
19
0;
0<
#1330000000
0!
0$
0,
01
09
#1335000000
1!
b001 #
1$
b001 &
1'
1,
1.
1/
10
11
15
19
#1340000000
0!
0$
0,
01
09
#1345000000
1!
b010 #
1$
b010 &
0'
1(
1,
0.
0/
00
11
13
14
05
16
19
#1350000000
0!
0$
0,
01
09
#1355000000
1!
b011 #
1$
b011 &
1'
1*
1,
1.
1/
10
11
15
17
18
19
#1360000000
0!
0$
0,
01
09
#1365000000
1!
b100 #
1$
b100 &
0'
0(
0*
1,
0.
0/
00
11
03
04
05
06
07
08
19
1;
1<
#1370000000
0!
0$
0,
01
09
#1375000000
1!
b101 #
1$
b101 &
1'
1,
1.
1/
10
11
15
19
#1380000000
0!
0$
0,
01
09
#1385000000
1!
b110 #
1$
b110 &
0'
1(
1,
0.
0/
00
11
13
14
05
16
19
#1390000000
0!
0$
0,
01
09
#1395000000
1!
b111 #
1$
b111 &
1'
1*
1,
1.
1/
10
11
15
17
18
19
#1400000000
0!
0$
0,
01
09
#1405000000
1!
b000 #
1$
b000 &
0'
0(
0*
1,
0.
0/
00
11
03
04
05
06
07
08
19
0;
0<
#1410000000
0!
0$
0,
01
09
#1415000000
1!
b001 #
1$
b001 &
1'
1,
1.
1/
10
11
15
19
#1420000000
0!
0$
0,
01
09
#1425000000
1!
b010 #
1$
b010 &
0'
1(
1,
0.
0/
00
11
13
14
05
16
19
#1430000000
0!
0$
0,
01
09
#1435000000
1!
b011 #
1$
b011 &
1'
1*
1,
1.
1/
10
11
15
17
18
19
#1440000000
0!
0$
0,
01
09
#1445000000
1!
b100 #
1$
b100 &
0'
0(
0*
1,
0.
0/
00
11
03
04
05
06
07
08
19
1;
1<
#1450000000
0!
0$
0,
01
09
#1455000000
1!
b101 #
1$
b101 &
1'
1,
1.
1/
10
11
15
19
#1460000000
0!
0$
0,
01
09
#1465000000
1!
b110 #
1$
b110 &
0'
1(
1,
0.
0/
00
11
13
14
05
16
19
#1470000000
0!
0$
0,
01
09
#1475000000
1!
b111 #
1$
b111 &
1'
1*
1,
1.
1/
10
11
15
17
18
19
#1480000000
0!
0$
0,
01
09
#1485000000
1!
b000 #
1$
b000 &
0'
0(
0*
1,
0.
0/
00
11
03
04
05
06
07
08
19
0;
0<
#1490000000
0!
0$
0,
01
09
#1495000000
1!
b001 #
1$
b001 &
1'
1,
1.
1/
10
11
15
19
#1500000000
0!
0$
0,
01
09
#1505000000
1!
b010 #
1$
b010 &
0'
1(
1,
0.
0/
00
11
13
14
05
16
19
#1510000000
0!
0$
0,
01
09
#1515000000
1!
b011 #
1$
b011 &
1'
1*
1,
1.
1/
10
11
15
17
18
19
#1520000000
0!
0$
0,
01
09
#1525000000
1!
b100 #
1$
b100 &
0'
0(
0*
1,
0.
0/
00
11
03
04
05
06
07
08
19
1;
1<
#1530000000
0!
0$
0,
01
09
#1535000000
1!
b101 #
1$
b101 &
1'
1,
1.
1/
10
11
15
19
#1540000000
0!
0$
0,
01
09
#1545000000
1!
b110 #
1$
b110 &
0'
1(
1,
0.
0/
00
11
13
14
05
16
19
#1550000000
0!
0$
0,
01
09
#1555000000
1!
b111 #
1$
b111 &
1'
1*
1,
1.
1/
10
11
15
17
18
19
#1560000000
0!
0$
0,
01
09
#1565000000
1!
b000 #
1$
b000 &
0'
0(
0*
1,
0.
0/
00
11
03
04
05
06
07
08
19
0;
0<
#1570000000
0!
0$
0,
01
09
#1575000000
1!
b001 #
1$
b001 &
1'
1,
1.
1/
10
11
15
19
#1580000000
0!
0$
0,
01
09
#1585000000
1!
b010 #
1$
b010 &
0'
1(
1,
0.
0/
00
11
13
14
05
16
19
#1590000000
0!
0$
0,
01
09
#1595000000
1!
b011 #
1$
b011 &
1'
1*
1,
1.
1/
10
11
15
17
18
19
#1600000000
0!
0$
0,
01
09
#1605000000
1!
b100 #
1$
b100 &
0'
0(
0*
1,
0.
0/
00
11
03
04
05
06
07
08
19
1;
1<
#1610000000
0!
0$
0,
01
09
#1615000000
1!
b101 #
1$
b101 &
1'
1,
1.
1/
10
11
15
19
#1620000000
0!
0$
0,
01
09
#1625000000
1!
b110 #
1$
b110 &
0'
1(
1,
0.
0/
00
11
13
14
05
16
19
#1630000000
0!
0$
0,
01
09
#1635000000
1!
b111 #
1$
b111 &
1'
1*
1,
1.
1/
10
11
15
17
18
19
#1640000000
0!
0$
0,
01
09
#1645000000
1!
b000 #
1$
b000 &
0'
0(
0*
1,
0.
0/
00
11
03
04
05
06
07
08
19
0;
0<
#1650000000
0!
0$
0,
01
09
#1655000000
1!
b001 #
1$
b001 &
1'
1,
1.
1/
10
11
15
19
#1660000000
0!
0$
0,
01
09
#1665000000
1!
b010 #
1$
b010 &
0'
1(
1,
0.
0/
00
11
13
14
05
16
19
#1670000000
0!
0$
0,
01
09
#1675000000
1!
b011 #
1$
b011 &
1'
1*
1,
1.
1/
10
11
15
17
18
19
#1680000000
0!
0$
0,
01
09
#1685000000
1!
b100 #
1$
b100 &
0'
0(
0*
1,
0.
0/
00
11
03
04
05
06
07
08
19
1;
1<
#1690000000
0!
0$
0,
01
09
#1695000000
1!
b101 #
1$
b101 &
1'
1,
1.
1/
10
11
15
19
#1700000000
0!
0$
0,
01
09
#1705000000
1!
b110 #
1$
b110 &
0'
1(
1,
0.
0/
00
11
13
14
05
16
19
#1710000000
0!
0$
0,
01
09
#1715000000
1!
b111 #
1$
b111 &
1'
1*
1,
1.
1/
10
11
15
17
18
19
#1720000000
0!
0$
0,
01
09
#1725000000
1!
b000 #
1$
b000 &
0'
0(
0*
1,
0.
0/
00
11
03
04
05
06
07
08
19
0;
0<
#1730000000
0!
0$
0,
01
09
#1735000000
1!
b001 #
1$
b001 &
1'
1,
1.
1/
10
11
15
19
#1740000000
0!
0$
0,
01
09
#1745000000
1!
b010 #
1$
b010 &
0'
1(
1,
0.
0/
00
11
13
14
05
16
19
#1750000000
0!
0$
0,
01
09
#1755000000
1!
b011 #
1$
b011 &
1'
1*
1,
1.
1/
10
11
15
17
18
19
#1760000000
0!
0$
0,
01
09
#1765000000
1!
b100 #
1$
b100 &
0'
0(
0*
1,
0.
0/
00
11
03
04
05
06
07
08
19
1;
1<
#1770000000
0!
0$
0,
01
09
#1775000000
1!
b101 #
1$
b101 &
1'
1,
1.
1/
10
11
15
19
#1780000000
0!
0$
0,
01
09
#1785000000
1!
b110 #
1$
b110 &
0'
1(
1,
0.
0/
00
11
13
14
05
16
19
#1790000000
0!
0$
0,
01
09
#1795000000
1!
b111 #
1$
b111 &
1'
1*
1,
1.
1/
10
11
15
17
18
19
#1800000000
0!
0$
0,
01
09
#1805000000
1!
b000 #
1$
b000 &
0'
0(
0*
1,
0.
0/
00
11
03
04
05
06
07
08
19
0;
0<
#1810000000
0!
0$
0,
01
09
#1815000000
1!
b001 #
1$
b001 &
1'
1,
1.
1/
10
11
15
19
#1820000000
0!
0$
0,
01
09
#1825000000
1!
b010 #
1$
b010 &
0'
1(
1,
0.
0/
00
11
13
14
05
16
19
#1830000000
0!
0$
0,
01
09
#1835000000
1!
b011 #
1$
b011 &
1'
1*
1,
1.
1/
10
11
15
17
18
19
#1840000000
0!
0$
0,
01
09
#1845000000
1!
b100 #
1$
b100 &
0'
0(
0*
1,
0.
0/
00
11
03
04
05
06
07
08
19
1;
1<
#1850000000
0!
0$
0,
01
09
#1855000000
1!
b101 #
1$
b101 &
1'
1,
1.
1/
10
11
15
19
#1860000000
0!
0$
0,
01
09
#1865000000
1!
b110 #
1$
b110 &
0'
1(
1,
0.
0/
00
11
13
14
05
16
19
#1870000000
0!
0$
0,
01
09
#1875000000
1!
b111 #
1$
b111 &
1'
1*
1,
1.
1/
10
11
15
17
18
19
#1880000000
0!
0$
0,
01
09
#1885000000
1!
b000 #
1$
b000 &
0'
0(
0*
1,
0.
0/
00
11
03
04
05
06
07
08
19
0;
0<
#1890000000
0!
0$
0,
01
09
#1895000000
1!
b001 #
1$
b001 &
1'
1,
1.
1/
10
11
15
19
#1900000000
0!
0$
0,
01
09
