Sequence Detection/detector.vhdl
library ieee;
use ieee.std_logic_1164.all;

entity sequence is
port (
    clk: in std_logic;
    rst: in std_logic;
    a: in std_logic;
    z: out std_logic
);
end sequence;

architecture seq_arch of sequence is
    type state is (q0, q1, q2, q3, q4);
    signal currentstate, nextstate: state;

begin

seq_proc: process(clk, rst) is
begin

if rst = '1' then
    currentstate <= q0;
elsif rising_edge(clk) then
    currentstate <= nextstate;
end if;

end process seq_proc;


comb_proc: process(currentstate, a) is
begin

case currentstate is

    when q0 =>
    if a = '1' then
   -- "1"
        nextstate <= q1;
    else
        nextstate <= q0;
    end if;
    
    when q1 =>
    if a = '0' then
    -- "10"
        nextstate <= q2;
    else
        nextstate <= q1;
    end if;  
    
    when q2 => 
    if a = '1' then
   -- "101"
        nextstate <= q3;
    else
        nextstate <= q0;
    end if;  
    
    when q3 =>
    if a = '1' then
    -- "1011"
        nextstate <= q4;
    else
        nextstate <= q0;
    end if; 
 
    when q4 =>
    if a = '0' then
        nextstate <= q0;
    else
        nextstate <= q1;
    end if;

end case;
end process comb_proc;

-- Output logic of the Sequence Detector
out_proc: process(currentstate) is
begin 
    case currentstate is
    when q0 =>
    z <= '0';
    
    when q1 =>
    z <= '0'; 
 
    when q2 => 
    z <= '0'; 
 
    when q3 =>
    z <= '0'; 
 
    when q4 =>
    z <= '1';
    
    end case;
end process out_proc;
end seq_arch;

Sequence Detection/detector_tb.vhdl
library ieee;
use ieee.std_logic_1164.all;
 
entity sd_tb is
end sd_tb;
 
architecture seq_arch of sd_tb is 
   
    component sequence
        port(
            clk : in  std_logic;
            rst : in  std_logic;
            a : in  std_logic;
            z : out  std_logic
        );
    end component;
    
    signal clk, rst, a : std_logic := '0';
    signal z : std_logic;

    constant clk_period : time := 10 ns;
 
begin
    uut: sequence port map (
        clk => clk,
        rst => rst,
        a => a,
        z => z
    );

    -- CLK process 
    clk_process: process
    begin
        clk <= '0';
        wait for clk_period/2;
        clk <= '1';
        wait for clk_period/2;
    end process;
 
    -- Stimulus process
    stimulus_process: process
    begin  
        a <= '0';
        rst <= '1';
        wait for 30 ns;

        rst <= '0';
        wait for 40 ns;

        a <= '0';
        wait for 10 ns;
        a <= '1';
        wait for 10 ns;
        a <= '1'; 
        wait for 10 ns;
        a <= '0'; 
        wait for 10 ns;
        a <= '1';
        wait for 10 ns;
        a <= '1'; 
        wait for 10 ns;
        a <= '0'; 
        -- insert stimulus here 

        wait;
    end process stimulus_process;

end seq_arch;

Sequence Detection/result.vcd
$date
  Sun Feb 11 02:19:01 2024
$end
$version
  GHDL v0
$end
$timescale
  1 fs
$end
$scope module standard $end
$upscope $end
$scope module std_logic_1164 $end
$upscope $end
$scope module sd_tb $end
$var reg 1 ! clk $end
$var reg 1 " rst $end
$var reg 1 # a $end
$var reg 1 $ z $end
$scope module uut $end
$var reg 1 % clk $end
$var reg 1 & rst $end
$var reg 1 ' a $end
$var reg 1 ( z $end
$comment currentstate is not handled $end
$comment nextstate is not handled $end
$upscope $end
$upscope $end
$enddefinitions $end
#0
0!
1"
0#
0$
0%
1&
0'
0(
#5000000
1!
1%
#10000000
0!
0%
#15000000
1!
1%
#20000000
0!
0%
#25000000
1!
1%
#30000000
0!
0"
0%
0&
#35000000
1!
1%
#40000000
0!
0%
#45000000
1!
1%
#50000000
0!
0%
#55000000
1!
1%
#60000000
0!
0%
#65000000
1!
1%
#70000000
0!
0%
#75000000
1!
1%
#80000000
0!
1#
0%
1'
#85000000
1!
1%
#90000000
0!
0%
#95000000
1!
1%
#100000000
0!
0#
0%
0'
#105000000
1!
1%
#110000000
0!
1#
0%
1'
#115000000
1!
1%
#120000000
0!
0%
#125000000
1!
1$
1%
1(
#130000000
0!
0#
0%
0'
#135000000
1!
0$
1%
0(
